massprince/__init__.py
massprince/vish1.py
massprince/vish2.py
massprince/vish3.py
massprince-1.0.dist-info/LICENSE
massprince-1.0.dist-info/METADATA
massprince-1.0.dist-info/WHEEL
massprince-1.0.dist-info/top_level.txt
massprince-1.0.dist-info/RECORD
